TEItransformer/__init__.py
TEItransformer/cssbuilder.py
TEItransformer/director.py
TEItransformer/docxbuilder.py
TEItransformer/docxconstructor.py
TEItransformer/htmlbuilder.py
TEItransformer/jsonbuilder.py
TEItransformer/loadsetup.py
TEItransformer/oddprocessor.py
TEItransformer/pathvalidator.py
TEItransformer/teiauxiliary.py
TEItransformer/teitransformer.py
TEItransformer/teixml.py
TEItransformer/xmlvalidators.py
TEItransformer/data/.DS_Store
TEItransformer/data/config/docx_constructor.yaml
TEItransformer/data/config/html_transformer.yaml
TEItransformer/data/config/tei_transformer.yaml
TEItransformer/data/css/.DS_Store
TEItransformer/data/css/base/.DS_Store
TEItransformer/data/css/drama/.DS_Store
TEItransformer/data/css/drama/docx/drama.css
TEItransformer/data/css/drama/html/drama.css
TEItransformer/data/css/plain/.DS_Store
TEItransformer/data/css/plain/docx/plain.css
TEItransformer/data/css/plain/html/.DS_Store
TEItransformer/data/css/plain/html/plain.css
TEItransformer/data/schema/.DS_Store
TEItransformer/data/schema/scenarios/.DS_Store
TEItransformer/data/schema/scenarios/drama/.DS_Store
TEItransformer/data/schema/scenarios/drama/dtd/tei_drama.dtd
TEItransformer/data/schema/scenarios/drama/rng/.DS_Store
TEItransformer/data/schema/scenarios/drama/rng/tei_drama.rng
TEItransformer/data/schema/scenarios/drama/xsd/.DS_Store
TEItransformer/data/schema/scenarios/drama/xsd/tei_drama.xsd
TEItransformer/data/schema/scenarios/drama/xsd/tei_drama_dcr.xsd
TEItransformer/data/schema/scenarios/drama/xsd/tei_drama_xml.xsd
TEItransformer/data/schema/scenarios/plain/.DS_Store
TEItransformer/data/schema/scenarios/plain/dtd/.DS_Store
TEItransformer/data/schema/scenarios/plain/dtd/plain.dtd
TEItransformer/data/schema/scenarios/plain/rng/.DS_Store
TEItransformer/data/schema/scenarios/plain/rng/plain.rng
TEItransformer/data/schema/scenarios/plain/xsd/.DS_Store
TEItransformer/data/schema/scenarios/plain/xsd/plain.xsd
TEItransformer/data/templates/document.html
TEItransformer-0.0.6.dist-info/METADATA
TEItransformer-0.0.6.dist-info/WHEEL
TEItransformer-0.0.6.dist-info/top_level.txt
TEItransformer-0.0.6.dist-info/RECORD
